Metadata-Version: 2.1
Name: asappy
Version: 0.0.2
Summary: A highly scalable approach to topic modelling in single-cell data by approximate pseudobulk projection
Home-page: UNKNOWN
Author: Sishir Subedi, Tomokazu S Sumida, Yongjin P Park
License: UNKNOWN
Platform: UNKNOWN
Requires-Python: >=3.7
